{
  "configurations": [
    {
      "name": "PROS Project",
      "includePath": [
        "${workspaceFolder}/**",
        "d:\\pros\\Lunar\\include",
        "c:\\Users\\user\\Documents\\GitHub\\Lunar\\include"
      ],
      "defines": [
        "_DEBUG",
        "UNICODE",
        "_UNICODE"
      ],
      "compilerPath": "c:\\Users\\user\\AppData\\Roaming\\Code\\User\\globalStorage\\sigbots.pros\\install\\pros-toolchain-windows\\usr\\bin\\arm-none-eabi-g++",
      "cStandard": "gnu11",
      "cppStandard": "gnu++20",
      "intelliSenseMode": "gcc-arm",
      "browse": {
        "path": [
          "c:\\Users\\user\\Documents\\GitHub\\Lunar"
        ],
        "limitSymbolsToIncludedHeaders": true,
        "databaseFilename": ""
      }
    }
  ],
  "version": 4
}